xlsx_evaluate/__init__.py
xlsx_evaluate/ast_nodes.py
xlsx_evaluate/evaluator.py
xlsx_evaluate/functions/date.py
xlsx_evaluate/functions/engineering.py
xlsx_evaluate/functions/financial.py
xlsx_evaluate/functions/func_xltypes.py
xlsx_evaluate/functions/information.py
xlsx_evaluate/functions/logical.py
xlsx_evaluate/functions/lookup.py
xlsx_evaluate/functions/math.py
xlsx_evaluate/functions/operator.py
xlsx_evaluate/functions/statistics.py
xlsx_evaluate/functions/text.py
xlsx_evaluate/functions/utils.py
xlsx_evaluate/functions/xl.py
xlsx_evaluate/functions/xlcriteria.py
xlsx_evaluate/functions/xlerrors.py
xlsx_evaluate/model.py
xlsx_evaluate/parser.py
xlsx_evaluate/patch.py
xlsx_evaluate/reader.py
xlsx_evaluate/tokenizer.py
xlsx_evaluate/utils.py
xlsx_evaluate/xltypes.py
xlsx_evaluate-0.5.0.dist-info/METADATA
xlsx_evaluate-0.5.0.dist-info/WHEEL
xlsx_evaluate-0.5.0.dist-info/RECORD
