Metadata-Version: 2.1
Name: xlsx-evaluate
Version: 0.5.0
Summary: Calculate XLSX formulas
Home-page: https://github.com/devind-team/xlsx_evaluate
License: MIT
Keywords: openpyxlsx,xlsx,formulas,evaluate
Author: Victor
Author-email: lyferov@yandex.ru
Requires-Python: >=3.9
Classifier: License :: OSI Approved :: MIT License
Classifier: Operating System :: OS Independent
Classifier: Programming Language :: Python :: 3
Classifier: Programming Language :: Python :: 3.9
Classifier: Programming Language :: Python :: 3.10
Classifier: Programming Language :: Python :: 3.11
Classifier: Programming Language :: Python :: 3
Requires-Dist: devind-yearfrac (>=1.0.0,<2.0.0)
Requires-Dist: jsonpickle (>=2.2.0,<3.0.0)
Requires-Dist: mock (>=4.0.3,<5.0.0)
Requires-Dist: numpy (>=1.22.4,<2.0.0)
Requires-Dist: numpy-financial (>=1.0.0,<2.0.0)
Requires-Dist: openpyxl (>=3.0.10,<4.0.0)
Requires-Dist: pandas (>=1.4.2,<2.0.0)
Requires-Dist: scipy (>=1.8.1,<2.0.0)
Project-URL: Repository, https://github.com/devind-team/xlsx_evaluate
